telegram_libs/__init__.py
telegram_libs/constants.py
telegram_libs/error.py
telegram_libs/handlers.py
telegram_libs/locales/en.json
telegram_libs/locales/ru.json
telegram_libs/logger.py
telegram_libs/mongo.py
telegram_libs/payment.py
telegram_libs/subscription.py
telegram_libs/support.py
telegram_libs/translation.py
telegram_libs/utils.py
telegram_libs-0.1.38.dist-info/LICENSE
telegram_libs-0.1.38.dist-info/METADATA
telegram_libs-0.1.38.dist-info/WHEEL
telegram_libs-0.1.38.dist-info/RECORD
